parsers/__init__.py
parsers/date_parser.py
parsers/ip_parser.py
parsers/log_parser.py
parsers/time_parser.py
ipv4_log_parser-0.1.0.dist-info/METADATA
ipv4_log_parser-0.1.0.dist-info/WHEEL
ipv4_log_parser-0.1.0.dist-info/top_level.txt
ipv4_log_parser-0.1.0.dist-info/RECORD
