Metadata-Version: 2.4
Name: ipv4-log-parser
Version: 0.1.0
Summary: A simple IPv4 log parser using regex, file handling, and data structures.
Author-email: khabar Hiba <hibakhabar@gmail.com>
License: MIT
Requires-Python: >=3.8
